{
  "groups": [
    {
      "name": "initinfo",
      "type": "com.wondersgroup.springbootconfigdemo.model.InitInfo",
      "sourceType": "com.wondersgroup.springbootconfigdemo.model.InitInfo"
    }
  ],
  "properties": [
    {
      "name": "initinfo.app-age",
      "type": "java.lang.Integer",
      "sourceType": "com.wondersgroup.springbootconfigdemo.model.InitInfo"
    },
    {
      "name": "initinfo.app-name",
      "type": "java.lang.String",
      "sourceType": "com.wondersgroup.springbootconfigdemo.model.InitInfo"
    },
    {
      "name": "initinfo.email",
      "type": "java.lang.String",
      "sourceType": "com.wondersgroup.springbootconfigdemo.model.InitInfo"
    },
    {
      "name": "initinfo.line-date",
      "type": "java.util.Date",
      "sourceType": "com.wondersgroup.springbootconfigdemo.model.InitInfo"
    },
    {
      "name": "initinfo.list-star",
      "type": "java.util.List<java.lang.Object>",
      "sourceType": "com.wondersgroup.springbootconfigdemo.model.InitInfo"
    },
    {
      "name": "initinfo.map-menu",
      "type": "java.util.Map<java.lang.String,java.lang.Object>",
      "sourceType": "com.wondersgroup.springbootconfigdemo.model.InitInfo"
    },
    {
      "name": "initinfo.on-line",
      "type": "java.lang.Boolean",
      "sourceType": "com.wondersgroup.springbootconfigdemo.model.InitInfo",
      "defaultValue": false
    },
    {
      "name": "initinfo.version-info",
      "type": "com.wondersgroup.springbootconfigdemo.model.Version",
      "sourceType": "com.wondersgroup.springbootconfigdemo.model.InitInfo"
    }
  ],
  "hints": []
}